<?xml version="1.0" encoding="utf-8" ?>
<dwsync>
<file name="head.php" server="C:/Program Files/xampp/htdocs/panamerican/" local="130250310069484000" remote="130250310060000000" Dst="0" />
<file name="footer.php" server="C:/Program Files/xampp/htdocs/panamerican/" local="130248800320000000" remote="130248800320000000" Dst="0" />
<file name="home.php" server="C:/Program Files/xampp/htdocs/panamerican/" local="130248810260000000" remote="130248810260000000" Dst="0" />
<file name="index.php" server="C:/Program Files/xampp/htdocs/panamerican/" local="130249547000000000" remote="130249547000000000" Dst="0" />
<file name="libros.php" server="C:/Program Files/xampp/htdocs/panamerican/" local="130250256371554000" remote="130250256370000000" Dst="0" />
<file name="editoriales.php" server="C:/Program Files/xampp/htdocs/panamerican/" local="130250264212944000" remote="130250264210000000" Dst="0" />
<file name="categorias.php" server="C:/Program Files/xampp/htdocs/panamerican/" local="130250344186224000" remote="130250344180000000" Dst="0" />
<file name="requerimiento.php" server="C:/wamp/www/panamerican/" local="130719194245127532" remote="130719194240000000" Dst="2" />
<file name="addVendedores.php" server="C:/wamp/www/panamerican/" local="130253714736012000" remote="130253714730000000" Dst="0" />
<file name="vendedores.php" server="C:/wamp/www/panamerican/" local="130279045157705569" remote="130279045150000000" Dst="0" />
<file name="libros.php" server="C:/wamp/www/panamerican/" local="130265791120000000" remote="130265791120000000" Dst="0" />
<file name="categorias.php" server="C:/wamp/www/panamerican/" local="130529033280000000" remote="130529033280000000" Dst="1" />
<file name="editoriales.php" server="C:/wamp/www/panamerican/" local="130252080274096000" remote="130252080270000000" Dst="0" />
<file name="addRequerimiento.php" server="C:/wamp/www/panamerican/" local="130719187906897037" remote="130719187900000000" Dst="1" />
<file name="head.php" server="C:/wamp/www/panamerican/" local="130720594601293977" remote="130720594600000000" Dst="1" />
<file name="addNotaRemision.php" server="C:/wamp/www/panamerican/" local="130693630140000000" remote="130693630140000000" Dst="1" />
<file name="verRemision.php" server="C:/wamp/www/panamerican/" local="130668336720000000" remote="130668336720000000" Dst="1" />
<file name="verRequerimiento.php" server="C:/wamp/www/panamerican/" local="130285130480000000" remote="130285130480000000" Dst="0" />
<file name="remision.php" server="C:/wamp/www/panamerican/" local="130717690480000000" remote="130717690480000000" Dst="1" />
<file name="notasIngreso.php" server="C:/wamp/www/panamerican/" local="130719273347104459" remote="130719273340000000" Dst="2" />
<file name="addIngreso.php" server="C:/wamp/www/panamerican/" local="130719239274085313" remote="130719239270000000" Dst="1" />
<file name="devolucion.php" server="C:/wamp/www/panamerican/" local="130720561626307450" remote="130720561620000000" Dst="2" />
<file name="kardexVendedor.php" server="C:/wamp/www/panamerican/" local="130717635920000000" remote="130717635920000000" Dst="1" />
<file name="addDevolucion.php" server="C:/wamp/www/panamerican/" local="130719203817286053" remote="130719203810000000" Dst="2" />
<file name="verDevolucion.php" server="C:/wamp/www/panamerican/" local="130269345880000000" remote="130269345880000000" Dst="0" />
<file name="yovendedor.php" server="C:/wamp/www/panamerican/" local="130265108320000000" remote="130265108320000000" Dst="0" />
<file name="yoremision.php" server="C:/wamp/www/panamerican/" local="130270134500000000" remote="130270134500000000" Dst="0" />
<file name="traspasoVendedores.php" server="C:/wamp/www/panamerican/" local="130265984760000000" remote="130265984760000000" Dst="0" />
<file name="addTraspaso.php" server="C:/wamp/www/panamerican/" local="130278095420000000" remote="130278095420000000" Dst="0" />
<file name="verTraspaso.php" server="C:/wamp/www/panamerican/" local="130292035532731913" remote="130292035530000000" Dst="0" />
<file name="almacenes.php" server="C:/wamp/www/panamerican/" local="130265108760000000" remote="130265108760000000" Dst="0" />
<file name="yovendedorStock.php" server="C:/wamp/www/panamerican/" local="130292089420000000" remote="130292089420000000" Dst="0" />
<file name="yorequerimiento.php" server="C:/wamp/www/panamerican/" local="130270139580000000" remote="130270139580000000" Dst="0" />
<file name="addContrato.php" server="C:/wamp/www/panamerican/" local="130720465551369810" remote="130720465550000000" Dst="2" />
<file name="contratos.php" server="C:/wamp/www/panamerican/" local="130720585387578460" remote="130720585380000000" Dst="2" />
<file name="ventas.php" server="C:/wamp/www/panamerican/" local="130700879412185382" remote="130700879410000000" Dst="1" />
<file name="editContrato.php" server="C:/wamp/www/panamerican/" local="130720461437586220" remote="130720461430000000" Dst="2" />
<file name="addPagoContrato.php" server="C:/wamp/www/panamerican/" local="130717893140000000" remote="130717893140000000" Dst="1" />
<file name="deudas.php" server="C:/wamp/www/panamerican/" local="130478198480000000" remote="130478198480000000" Dst="2" />
<file name="addCuenta.php" server="C:/wamp/www/panamerican/" local="130719524218994773" remote="130719524210000000" Dst="1" />
<file name="regVentaContrato.php" server="C:/wamp/www/panamerican/" local="130381470380000000" remote="130381470380000000" Dst="2" />
<file name="contratosVentas.php" server="C:/wamp/www/panamerican/" local="130699098866515564" remote="130699098860000000" Dst="1" />
<file name="editContratoPost.php" server="C:/wamp/www/panamericanSantaCruz/" local="130583779520000000" remote="130583779520000000" Dst="2" />
<file name="editContrato.php" server="C:/wamp/www/panamericanSantaCruz/" local="130583731460000000" remote="130583731460000000" Dst="2" />
<file name="remision.php" server="C:/wamp/www/panamericanSantaCruz/" local="130585341840000000" remote="130585341840000000" Dst="2" />
<file name="devolucion.php" server="C:/wamp/www/panamericanSantaCruz/" local="130583415440000000" remote="130583415440000000" Dst="2" />
<file name="addIngreso.php" server="C:/wamp/www/panamericanSantaCruz/" local="130584053565234725" remote="130584053560000000" Dst="2" />
<file name="addRequerimiento.php" server="C:/wamp/www/panamericanSantaCruz/" local="130584134704256760" remote="130584134700000000" Dst="2" />
<file name="addNotaRemision.php" server="C:/wamp/www/panamericanSantaCruz/" local="130525286520000000" remote="130525286520000000" Dst="2" />
<file name="head.php" server="C:/wamp/www/panamericanSantaCruz/" local="130584425360000000" remote="130584425360000000" Dst="2" />
<file name="addDevolucion.php" server="C:/wamp/www/panamericanSantaCruz/" local="130584161901200005" remote="130584161900000000" Dst="2" />
<file name="addEgreso.php" server="C:/wamp/www/panamericanSantaCruz/" local="130528940600000000" remote="130528940600000000" Dst="2" />
<file name="addTraspaso.php" server="C:/wamp/www/panamericanSantaCruz/" local="130538333440000000" remote="130538333440000000" Dst="2" />
<file name="addTraspasoAlmacen.php" server="C:/wamp/www/panamericanSantaCruz/" local="130538775220000000" remote="130538775220000000" Dst="2" />
<file name="addDeuda.php" server="C:/wamp/www/panamericanSantaCruz/" local="130476412920000000" remote="130476412920000000" Dst="2" />
<file name="addVendedores.php" server="C:/wamp/www/panamericanSantaCruz/" local="130546684440000000" remote="130546684440000000" Dst="2" />
<file name="comportamientoVentas.php" server="C:/wamp/www/panamericanSantaCruz/" local="130530597940000000" remote="130530597940000000" Dst="2" />
<file name="addNotaRemision.php" server="C:/xampp/htdocs/panamerican/" local="130659987500000000" remote="130659987500000000" Dst="1" />
<file name="verRemision.php" server="C:/xampp/htdocs/panamerican/" local="130659989240000000" remote="130659989240000000" Dst="1" />
<file name="verEgreso.php" server="C:/xampp/htdocs/panamerican/" local="130549928420000000" remote="130549928420000000" Dst="2" />
<file name="addEgreso.php" server="C:/xampp/htdocs/panamerican/" local="130584204380000000" remote="130584204380000000" Dst="1" />
<file name="notasEgreso.php" server="C:/xampp/htdocs/panamerican/" local="130669652840000000" remote="130669652840000000" Dst="1" />
<file name="verResumenCargos.php" server="C:/xampp/htdocs/panamerican/" local="130320348320000000" remote="130320348320000000" Dst="1" />
<file name="registroInventario.php" server="C:/xampp/htdocs/panamerican/" local="130696226253988904" remote="130696226250000000" Dst="1" />
<file name="kardexVendedor.php" server="C:/xampp/htdocs/panamerican/" local="130704834630790520" remote="130704834630000000" Dst="1" />
<file name="editContratoPost.php" server="C:/xampp/htdocs/panamerican/" local="130687318880000000" remote="130687318880000000" Dst="1" />
<file name="head.php" server="C:/xampp/htdocs/panamerican/" local="130693631840000000" remote="130693631840000000" Dst="1" />
<file name="registroCatalogo.php" server="C:/xampp/htdocs/panamerican/" local="130660032690000000" remote="130660032690000000" Dst="1" />
<file name="libros.php" server="C:/xampp/htdocs/panamerican/" local="130548329240000000" remote="130548329240000000" Dst="1" />
<file name="addContrato.php" server="C:/xampp/htdocs/panamerican/" local="130685477860000000" remote="130685477860000000" Dst="1" />
<file name="anularDiferido.php" server="C:/xampp/htdocs/panamerican/" local="130699128878956636" remote="130699128870000000" Dst="1" />
<file name="addPagos.php" server="C:/xampp/htdocs/panamerican/" local="130668084426093117" remote="130668084420000000" Dst="2" />
<file name="addCuenta.php" server="C:/xampp/htdocs/panamerican/" local="130745417630603487" remote="130745417630000000" Dst="1" />
<file name="verTarjetaCobranza.php" server="C:/xampp/htdocs/panamerican/" local="130668115540000000" remote="130668115540000000" Dst="1" />
<file name="cuentas.php" server="C:/xampp/htdocs/panamerican/" local="130667746557886172" remote="130667746550000000" Dst="2" />
<file name="produccionOrganizacion.php" server="C:/xampp/htdocs/panamerican/" local="130700922871629885" remote="130700922870000000" Dst="1" />
<file name="contratosVentas.php" server="C:/xampp/htdocs/panamerican/" local="130696256140000000" remote="130696256140000000" Dst="1" />
<file name="cuotas.php" server="C:/xampp/htdocs/panamerican/" local="130668091537546396" remote="130668091530000000" Dst="1" />
<file name="contratos.php" server="C:/xampp/htdocs/panamerican/" local="130698591180000000" remote="130698591180000000" Dst="1" />
<file name="remision.php" server="C:/xampp/htdocs/panamerican/" local="130669651580000000" remote="130669651580000000" Dst="1" />
<file name="pagos.php" server="C:/xampp/htdocs/panamerican/" local="130569801680000000" remote="130569801680000000" Dst="1" />
<file name="listaPagos.php" server="C:/xampp/htdocs/panamerican/" local="130668099870000000" remote="130668099870000000" Dst="1" />
<file name="verCuenta.php" server="C:/xampp/htdocs/panamerican/" local="130668124934673585" remote="130668124930000000" Dst="1" />
<file name="index.php" server="C:/xampp/htdocs/panamerican/" local="130607815660000000" remote="130607815660000000" Dst="1" />
<file name="verIngreso.php" server="C:/xampp/htdocs/panamerican/" local="130585501500000000" remote="130585501500000000" Dst="1" />
<file name="addReferencias.php" server="C:/xampp/htdocs/panamerican/" local="130564725820000000" remote="130564725820000000" Dst="2" />
<file name="registroVentas.php" server="C:/xampp/htdocs/panamerican/" local="130475747640000000" remote="130475747640000000" Dst="2" />
<file name="addPagoContrato.php" server="C:/xampp/htdocs/panamerican/" local="130591423060000000" remote="130591423060000000" Dst="1" />
<file name="almacenes.php" server="C:/xampp/htdocs/panamerican/" local="130669653340000000" remote="130669653340000000" Dst="1" />
<file name="addRequerimiento.php" server="C:/xampp/htdocs/panamerican/" local="130584193480000000" remote="130584193480000000" Dst="1" />
<file name="contratosAnulados.php" server="C:/xampp/htdocs/panamerican/" local="130571498240000000" remote="130571498240000000" Dst="1" />
<file name="registroKardexVendedor.php" server="C:/xampp/htdocs/panamerican/" local="130582917140000000" remote="130582917140000000" Dst="1" />
<file name="anularCuenta.php" server="C:/xampp/htdocs/panamerican/" local="130697954180000000" remote="130697954180000000" Dst="1" />
<file name="addIngresoVenta.php" server="C:/xampp/htdocs/panamerican/" local="130314966920000000" remote="130314966920000000" Dst="1" />
<file name="devolucionObrasAdmin.php" server="C:/xampp/htdocs/panamerican/" local="130329582040000000" remote="130329582040000000" Dst="1" />
<file name="devoluciones.php" server="C:/xampp/htdocs/panamerican/" local="130464727920000000" remote="130464727920000000" Dst="1" />
<file name="devolucion.php" server="C:/xampp/htdocs/panamerican/" local="130669651960000000" remote="130669651960000000" Dst="1" />
<file name="addDevolucion.php" server="C:/xampp/htdocs/panamerican/" local="130584207740000000" remote="130584207740000000" Dst="1" />
<file name="addDevolucionContratos.php" server="C:/xampp/htdocs/panamerican/" local="130538404860000000" remote="130538404860000000" Dst="1" />
<file name="addDevolucionDeudas.php" server="C:/xampp/htdocs/panamerican/" local="130476666740000000" remote="130476666740000000" Dst="1" />
<file name="devolucionCuentas.php" server="C:/xampp/htdocs/panamerican/" local="130335800160000000" remote="130335800160000000" Dst="1" />
<file name="editContrato.php" server="C:/xampp/htdocs/panamerican/" local="130687315860000000" remote="130687315860000000" Dst="1" />
<file name="devolucionVentas.php" server="C:/xampp/htdocs/panamerican/" local="130308843260000000" remote="130308843260000000" Dst="1" />
<file name="ventas.php" server="C:/xampp/htdocs/panamerican/" local="130519728700000000" remote="130519728700000000" Dst="1" />
<file name="produccionMensualVentas.php" server="C:/xampp/htdocs/panamerican/" local="130519749280000000" remote="130519749280000000" Dst="1" />
<file name="produccionDiariaVentas.php" server="C:/xampp/htdocs/panamerican/" local="130519744740000000" remote="130519744740000000" Dst="1" />
<file name="relacionObrasVendidas.php" server="C:/xampp/htdocs/panamerican/" local="130700913802591732" remote="130700913800000000" Dst="1" />
<file name="comportamientoVentas.php" server="C:/xampp/htdocs/panamerican/" local="130530633940000000" remote="130530633940000000" Dst="1" />
<file name="kardexMayor.php" server="C:/wamp/www/panamerican/" local="130712581360000000" remote="130712581360000000" Dst="1" />
<file name="relacionObrasVendidas.php" server="C:/wamp/www/panamerican/" local="130704823683917047" remote="130704823680000000" Dst="1" />
<file name="comportamientoVentas.php" server="C:/wamp/www/panamerican/" local="130701019136803278" remote="130701019130000000" Dst="1" />
<file name="cierres.php" server="C:/wamp/www/panamerican/" local="130681442980000000" remote="130681442980000000" Dst="1" />
<file name="anularCuenta.php" server="C:/wamp/www/panamerican/" local="130716418260000000" remote="130716418260000000" Dst="1" />
<file name="addIngresoVenta.php" server="C:/wamp/www/panamerican/" local="130716673760000000" remote="130716673760000000" Dst="1" />
<file name="devolucionObrasAdmin.php" server="C:/wamp/www/panamerican/" local="130329582040000000" remote="130329582040000000" Dst="1" />
<file name="devolucionObras.php" server="C:/wamp/www/panamerican/" local="130717510351395893" remote="130717510350000000" Dst="1" />
<file name="devolucionVentasCobranza.php" server="C:/wamp/www/panamerican/" local="130716378940000000" remote="130716378940000000" Dst="1" />
<file name="refinanciamiento.php" server="C:/wamp/www/panamerican/" local="130716391540000000" remote="130716391540000000" Dst="1" />
<file name="cuentas.php" server="C:/wamp/www/panamerican/" local="130667746560000000" remote="130667746560000000" Dst="1" />
<file name="cuotas.php" server="C:/wamp/www/panamerican/" local="130744535060000000" remote="130744535060000000" Dst="1" />
<file name="cambioObras.php" server="C:/wamp/www/panamerican/" local="130717483440236939" remote="130717483440000000" Dst="1" />
<file name="listarCambioObras.php" server="C:/wamp/www/panamerican/" local="130717524311720928" remote="130717524310000000" Dst="1" />
<file name="devolucionVentas.php" server="C:/wamp/www/panamerican/" local="130717508535848054" remote="130717508530000000" Dst="1" />
<file name="devolucionAlmacen.php" server="C:/wamp/www/panamerican/" local="130464697280000000" remote="130464697280000000" Dst="1" />
<file name="cambioObrasAlmacen.php" server="C:/wamp/www/panamerican/" local="130717516960000000" remote="130717516960000000" Dst="1" />
<file name="addCambioObrasAlmacen.php" server="C:/wamp/www/panamerican/" local="130717589850000000" remote="130717589850000000" Dst="1" />
<file name="addEgreso.php" server="C:/wamp/www/panamerican/" local="130717682220000000" remote="130717682220000000" Dst="1" />
<file name="verCuenta.php" server="C:/wamp/www/panamerican/" local="130668337700000000" remote="130668337700000000" Dst="1" />
<file name="verTarjetaCobranza.php" server="C:/wamp/www/panamerican/" local="130693618560000000" remote="130693618560000000" Dst="1" />
<file name="verEgreso.php" server="C:/wamp/www/panamerican/" local="130744562180000000" remote="130744562180000000" Dst="1" />
<file name="verCambioObra.php" server="C:/wamp/www/panamerican/" local="130718044130000000" remote="130718044130000000" Dst="1" />
<file name="devoluciones.php" server="C:/wamp/www/panamerican/" local="130719205764809742" remote="130719205760000000" Dst="1" />
<file name="notasEgreso.php" server="C:/wamp/www/panamerican/" local="130719274962018211" remote="130719274960000000" Dst="2" />
<file name="addTraspasoAlmacen.php" server="C:/wamp/www/panamerican/" local="130717683360000000" remote="130717683360000000" Dst="1" />
<file name="traspasoAlmacen.php" server="C:/wamp/www/panamerican/" local="130586236240000000" remote="130586236240000000" Dst="1" />
<file name="addDevolucionContratos.php" server="C:/wamp/www/panamerican/" local="130717684060000000" remote="130717684060000000" Dst="1" />
<file name="editContratoEspera.php" server="C:/wamp/www/panamerican/" local="130584634860000000" remote="130584634860000000" Dst="1" />
<file name="anularDiferido.php" server="C:/wamp/www/panamerican/" local="130699128880000000" remote="130699128880000000" Dst="1" />
<file name="contratosFacturados.php" server="C:/wamp/www/panamerican/" local="130564761220000000" remote="130564761220000000" Dst="1" />
<file name="addReferencias.php" server="C:/wamp/www/panamerican/" local="130744547400000000" remote="130744547400000000" Dst="1" />
<file name="addCobradores.php" server="C:/wamp/www/panamerican/" local="130287264720000000" remote="130287264720000000" Dst="1" />
<file name="editCobradores.php" server="C:/wamp/www/panamerican/" local="130287261640000000" remote="130287261640000000" Dst="1" />
<file name="cobranzas.php" server="C:/wamp/www/panamerican/" local="130287227740000000" remote="130287227740000000" Dst="1" />
<file name="cobradores.php" server="C:/wamp/www/panamerican/" local="130606949660000000" remote="130606949660000000" Dst="1" />
<file name="addPagos.php" server="C:/wamp/www/panamerican/" local="130744538300000000" remote="130744538300000000" Dst="1" />
<file name="editContratoPost.php" server="C:/wamp/www/panamerican/" local="130720403386577164" remote="130720403380000000" Dst="2" />
<file name="produccionOrganizacion.php" server="C:/wamp/www/panamerican/" local="130701103920000000" remote="130701103920000000" Dst="1" />
<file name="produccionDiariaVentas.php" server="C:/wamp/www/panamerican/" local="130701102700000000" remote="130701102700000000" Dst="1" />
<file name="cuotasIniciales.php" server="C:/wamp/www/panamerican/" local="130720354424029583" remote="130720354420000000" Dst="1" />
<file name="produccionMensualVentas.php" server="C:/wamp/www/panamerican/" local="130700925180000000" remote="130700925180000000" Dst="1" />
<file name="error.php" server="C:/wamp/www/panamerican/" local="130264937200000000" remote="130264937200000000" Dst="1" />
<file name="addLibros.php" server="C:/wamp/www/panamerican/" local="130373708500000000" remote="130373708500000000" Dst="1" />
<file name="reportePagosCuotaInicial.php" server="C:/wamp/www/panamerican/" local="130720597650000000" remote="130720597650000000" Dst="1" />
<file name="verFilasKardex.php" server="C:/wamp/www/panamerican/" local="130558721520000000" remote="130558721520000000" Dst="2" />
</dwsync>